myqiwi/__init__.py
myqiwi/client.py
myqiwi/exceptions.py
myqiwi/request.py
myqiwi/utils.py
myqiwi/webhook/__init__.py
myqiwi/webhook/fastapi_server.py
tests/__init__.py
tests/test_qiwi.py
myqiwi-0.1.dist-info/METADATA
myqiwi-0.1.dist-info/WHEEL
myqiwi-0.1.dist-info/top_level.txt
myqiwi-0.1.dist-info/RECORD
