Metadata-Version: 2.1
Name: myqiwi
Version: 0.1
Summary: Python qiwi api for Humans.
Author: alteralt
License: MIT
Project-URL: Source, https://github.com/alteralt/myqiwi
Classifier: Development Status :: 5 - Production/Stable
Classifier: Intended Audience :: Developers
Classifier: Natural Language :: Russian
Classifier: Programming Language :: Python
Classifier: Programming Language :: Python :: 3.8
Requires-Python: >=3.5
Requires-Dist: aiohttp (>=3.6.3)
